bezier.libs/libquadmath-96973f99.so.0.0.0
bezier.libs/libbezier-e5395c70.so.2024.6.20
bezier.libs/libgfortran-040039e1.so.5.0.0
bezier-2024.6.20.dist-info/zip-safe
bezier-2024.6.20.dist-info/LICENSE
bezier-2024.6.20.dist-info/WHEEL
bezier-2024.6.20.dist-info/top_level.txt
bezier-2024.6.20.dist-info/RECORD
bezier-2024.6.20.dist-info/METADATA
bezier/_geometric_intersection.py
bezier/curved_polygon.py
bezier/_curve_intersection.pxd
bezier/_curve.pxd
bezier/__config__.py
bezier/_speedup.cpython-311-x86_64-linux-gnu.so
bezier/_triangle_intersection.py
bezier/_triangle_helpers.py
bezier/_plot_helpers.py
bezier/curve.py
bezier/_triangle.pxd
bezier/_helpers.py
bezier/_base.py
bezier/_triangle_intersection.pxd
bezier/_curve_helpers.py
bezier/_intersection_helpers.py
bezier/triangle.py
bezier/_helpers.pxd
bezier/_symbolic.py
bezier/_status.pxd
bezier/__init__.py
bezier/hazmat/helpers.py
bezier/hazmat/intersection_helpers.py
bezier/hazmat/triangle_helpers.py
bezier/hazmat/clipping.py
bezier/hazmat/algebraic_intersection.py
bezier/hazmat/curve_helpers.py
bezier/hazmat/geometric_intersection.py
bezier/hazmat/triangle_intersection.py
bezier/hazmat/__init__.py
