Metadata-Version: 2.1
Name: bezier
Version: 2024.6.20
Summary: Helper for Bézier Curves, Triangles, and Higher Order Objects
Home-page: https://github.com/dhermes/bezier
Author: Danny Hermes
Author-email: daniel.j.hermes@gmail.com
License: Apache 2.0
Project-URL: Documentation, https://bezier.readthedocs.io/
Project-URL: Changelog, https://bezier.readthedocs.io/en/latest/releases/index.html
Project-URL: Issue Tracker, https://github.com/dhermes/bezier/issues
Keywords: Geometry,Curve,Bezier,Intersection,Python
Platform: Posix; macOS; Windows
Classifier: Development Status :: 4 - Beta
Classifier: Intended Audience :: Developers
Classifier: Intended Audience :: Science/Research
Classifier: Topic :: Scientific/Engineering :: Mathematics
Classifier: License :: OSI Approved :: Apache Software License
Classifier: Operating System :: OS Independent
Classifier: Programming Language :: Python :: 3
Classifier: Programming Language :: Python :: 3.10
Classifier: Programming Language :: Python :: 3.11
Classifier: Programming Language :: Python :: 3.12
Classifier: Programming Language :: Python :: Implementation :: CPython
Classifier: Programming Language :: Python :: Implementation :: PyPy
Requires-Python: >=3.10
License-File: LICENSE
Requires-Dist: numpy >=2.0.0
Provides-Extra: full
Requires-Dist: matplotlib >=3.9.0 ; extra == 'full'
Requires-Dist: scipy >=1.13.1 ; extra == 'full'
Requires-Dist: sympy >=1.12.1 ; extra == 'full'
